{
    "deckdeckgo-starter": {
        "branch": "studio",
        "description": "The Progressive Web App alternative for simple presentations",
        "homepage": "https://deckdeckgo.com",
        "owner": "deckgo",
        "repo": "deckdeckgo-starter",
        "rev": "82bc4a368f6e7416c516771f47bc1c6417286f33",
        "sha256": "1ajfczwcl2x8y126bc4jxqdm6dk0xzvpswl224r50gcsssn08nwv",
        "type": "tarball",
        "url": "https://github.com/deckgo/deckdeckgo-starter/archive/82bc4a368f6e7416c516771f47bc1c6417286f33.tar.gz",
        "url_template": "https://github.com/<owner>/<repo>/archive/<rev>.tar.gz"
    },
    "elasticmq": {
        "sha256": "1cp2pmkc6gx7gr6109jlcphlky5rr6s1wj528r6hyhzdc01sjhhz",
        "type": "file",
        "url": "https://s3-eu-west-1.amazonaws.com/softwaremill-public/elasticmq-server-0.14.6.jar",
        "url_template": "https://s3-eu-west-1.amazonaws.com/softwaremill-public/elasticmq-server-0.14.6.jar"
    },
    "hs-jose": {
        "branch": "master",
        "description": "Haskell JOSE and JWT library",
        "homepage": "http://hackage.haskell.org/package/jose",
        "owner": "frasertweedale",
        "repo": "hs-jose",
        "rev": "71274bf64c0600c1d877152173a08a5bff7adf4d",
        "sha256": "0ah189vika1s0jk8f17mn77gilkw24vbs6xlggxw1qj926i6c4pk",
        "type": "tarball",
        "url": "https://github.com/frasertweedale/hs-jose/archive/71274bf64c0600c1d877152173a08a5bff7adf4d.tar.gz",
        "url_template": "https://github.com/<owner>/<repo>/archive/<rev>.tar.gz"
    },
    "napalm": {
        "branch": "master",
        "description": "Support for building npm packages in Nix and lightweight npm registry",
        "homepage": "",
        "owner": "nmattia",
        "repo": "napalm",
        "rev": "0331a5b586a186c966f816d434bd5c1ecfa16089",
        "sha256": "14nlqmmv3xx4cf3r9kcw2xbfgpddppw27ygp8s3r0bbccgwcp9gi",
        "type": "tarball",
        "url": "https://github.com/nmattia/napalm/archive/0331a5b586a186c966f816d434bd5c1ecfa16089.tar.gz",
        "url_template": "https://github.com/<owner>/<repo>/archive/<rev>.tar.gz"
    },
    "niv": {
        "branch": "master",
        "description": "Easy dependency management for Nix projects",
        "homepage": "https://github.com/nmattia/niv",
        "owner": "nmattia",
        "repo": "niv",
        "rev": "c2698b0780b783880e0b1a520723948fe3b5c26a",
        "sha256": "0v68x0h9si6kjqg5fcjrgsbsf4x18m32a786yvjmrdkrki9qwmcq",
        "type": "tarball",
        "url": "https://github.com/nmattia/niv/archive/c2698b0780b783880e0b1a520723948fe3b5c26a.tar.gz",
        "url_template": "https://github.com/<owner>/<repo>/archive/<rev>.tar.gz"
    },
    "nixpkgs": {
        "branch": "release-19.09",
        "description": "Nixpkgs/NixOS branches that track the Nixpkgs/NixOS channels",
        "homepage": null,
        "owner": "NixOS",
        "repo": "nixpkgs",
        "rev": "db5273ce2abd66117e1ee8affc8098c75238489f",
        "sha256": "1fvmkvh7jgi9a2k09bhjv3gv8cbnxaii6rn0ka6m34kwdl0zwswv",
        "type": "tarball",
        "url": "https://github.com/NixOS/nixpkgs/archive/db5273ce2abd66117e1ee8affc8098c75238489f.tar.gz",
        "url_template": "https://github.com/<owner>/<repo>/archive/<rev>.tar.gz"
    },
    "port-utils": {
        "sha256": "1vfmm8mmkmfffgza64h6qz4ibniibqdr8mj452ikp1xmvv6m8qm9",
        "type": "tarball",
        "url": "http://hackage.haskell.org/package/port-utils-0.2.1.0/port-utils-0.2.1.0.tar.gz",
        "url_template": "http://hackage.haskell.org/package/port-utils-0.2.1.0/port-utils-0.2.1.0.tar.gz"
    },
    "static-haskell-nix": {
        "branch": "master",
        "description": "easily build most Haskell programs into fully static Linux executables",
        "homepage": "",
        "owner": "nh2",
        "repo": "static-haskell-nix",
        "rev": "8d004d7ced9da947c785b93b4011f39367442339",
        "sha256": "0nw4g23c5rs0cvaar2phpr60zim9r0qycznpifi8d8k85y4r3bdd",
        "type": "tarball",
        "url": "https://github.com/nh2/static-haskell-nix/archive/8d004d7ced9da947c785b93b4011f39367442339.tar.gz",
        "url_template": "https://github.com/<owner>/<repo>/archive/<rev>.tar.gz"
    },
    "terraform": {
        "branch": "master",
        "description": "Terraform enables you to safely and predictably create, change, and improve infrastructure. It is an open source tool that codifies APIs into declarative configuration files that can be shared amongst team members, treated as code, edited, reviewed, and versioned.",
        "homepage": "https://www.terraform.io/",
        "owner": "hashicorp",
        "repo": "terraform",
        "rev": "v0.12.18",
        "sha256": "1p2rvs9dw2rzzggf3q2lifwbd82b7xb3jpb4yz5nmggn5g22qlc1",
        "type": "tarball",
        "url": "https://github.com/hashicorp/terraform/archive/v0.12.18.tar.gz",
        "url_template": "https://github.com/<owner>/<repo>/archive/<rev>.tar.gz"
    },
    "terraform-provider-aws": {
        "branch": "master",
        "description": "Terraform AWS provider",
        "homepage": "https://www.terraform.io/docs/providers/aws/",
        "owner": "terraform-providers",
        "repo": "terraform-provider-aws",
        "rev": "f1629af0aa159240fdd8d2fdd294f49b79cc17f6",
        "sha256": "0969fcysh0jsdicjm3fgx3jx39rzizbal2blvgnf9fsaqi73z3gx",
        "type": "tarball",
        "url": "https://github.com/terraform-providers/terraform-provider-aws/archive/f1629af0aa159240fdd8d2fdd294f49b79cc17f6.tar.gz",
        "url_template": "https://github.com/<owner>/<repo>/archive/<rev>.tar.gz"
    },
    "terraform-provider-external": {
        "branch": "master",
        "description": "Terraform external provider",
        "homepage": "https://www.terraform.io/docs/providers/external/",
        "owner": "terraform-providers",
        "repo": "terraform-provider-external",
        "rev": "961bccb7b3e1ed38f941465574378cc1da094c64",
        "sha256": "1g0s5lpnhxp23b8n4vqjnlwirz86d6xm4jab0spdywh3pdiwjd7c",
        "type": "tarball",
        "url": "https://github.com/terraform-providers/terraform-provider-external/archive/961bccb7b3e1ed38f941465574378cc1da094c64.tar.gz",
        "url_template": "https://github.com/<owner>/<repo>/archive/<rev>.tar.gz"
    },
    "wai-lambda": {
        "branch": "master",
        "description": "Haskell Webapps on AWS Lambda",
        "owner": "deckgo",
        "repo": "wai-lambda",
        "rev": "7f139047addff89e9d30e55b7eebb07c0e846456",
        "sha256": "0qqi6wlg8v35dkh6gh9mrj0kb9kpzrz2pc7k0dykk2ahcj6m22k6",
        "type": "tarball",
        "url": "https://github.com/deckgo/wai-lambda/archive/7f139047addff89e9d30e55b7eebb07c0e846456.tar.gz",
        "url_template": "https://github.com/<owner>/<repo>/archive/<rev>.tar.gz"
    }
}
